pycosmiconfig/__init__.py
pycosmiconfig/port/ExplorerBase.py
pycosmiconfig/port/ExplorerSync.py
pycosmiconfig/port/index.py
pycosmiconfig/port/loaders.py
pycosmiconfig/port/types.py
pycosmiconfig/port/util.py
pycosmiconfig/tests/test_meta_config.py
pycosmiconfig/tests/test_util.py
pycosmiconfig/tests/util.py
pycosmiconfig/utils.py
pycosmiconfig-8.3.6.dist-info/LICENSE
pycosmiconfig-8.3.6.dist-info/METADATA
pycosmiconfig-8.3.6.dist-info/WHEEL
pycosmiconfig-8.3.6.dist-info/entry_points.txt
pycosmiconfig-8.3.6.dist-info/RECORD
