Metadata-Version: 2.1
Name: pycosmiconfig
Version: 8.3.6
Summary: Python port of Cosmiconfig. Find and load configuration from a pyproject.toml property, rc file, Python file, and more!
Home-page: https://github.com/jurooravec/pycosmiconfig
License: MIT
Keywords: cosmiconfig,config,configuration,preferences,settings,setup,json,yaml,yml,toml,tml
Author: Juro Oravec
Author-email: juraj.oravec.josefson@gmail.com
Maintainer: Juro Oravec
Maintainer-email: juraj.oravec.josefson@gmail.com
Requires-Python: >=3.8,<4.0
Classifier: License :: OSI Approved :: MIT License
Classifier: Programming Language :: Python :: 3
Classifier: Programming Language :: Python :: 3.8
Classifier: Programming Language :: Python :: 3.9
Classifier: Programming Language :: Python :: 3.10
Classifier: Programming Language :: Python :: 3.11
Requires-Dist: pydantic (>=1.10.2,<2.0.0)
Requires-Dist: pyyaml (>=6.0.1,<7.0.0)
Requires-Dist: toml (>=0.10.2,<0.11.0)
Project-URL: Documentation, https://github.com/jurooravec/pycosmiconfig
Project-URL: Repository, https://github.com/jurooravec/pycosmiconfig
